pyaltiumlib/__init__.py
pyaltiumlib/base.py
pyaltiumlib/libcomponent.py
pyaltiumlib/datatypes/__init__.py
pyaltiumlib/datatypes/binaryreader.py
pyaltiumlib/datatypes/coordinate.py
pyaltiumlib/datatypes/mapping.py
pyaltiumlib/datatypes/parametercollection.py
pyaltiumlib/datatypes/parametercolor.py
pyaltiumlib/datatypes/parameterfont.py
pyaltiumlib/datatypes/pcblayerdefinition.py
pyaltiumlib/datatypes/pcbmapping.py
pyaltiumlib/datatypes/schematicmapping.py
pyaltiumlib/pcblib/__init__.py
pyaltiumlib/pcblib/footprint.py
pyaltiumlib/pcblib/lib.py
pyaltiumlib/pcblib/records/PCBArc.py
pyaltiumlib/pcblib/records/PCBComponentBody.py
pyaltiumlib/pcblib/records/PCBFill.py
pyaltiumlib/pcblib/records/PCBPad.py
pyaltiumlib/pcblib/records/PCBRegion.py
pyaltiumlib/pcblib/records/PCBString.py
pyaltiumlib/pcblib/records/PCBTrack.py
pyaltiumlib/pcblib/records/PCBVia.py
pyaltiumlib/pcblib/records/__init__.py
pyaltiumlib/pcblib/records/base.py
pyaltiumlib/schlib/__init__.py
pyaltiumlib/schlib/lib.py
pyaltiumlib/schlib/symbol.py
pyaltiumlib/schlib/records/SchArc.py
pyaltiumlib/schlib/records/SchBezier.py
pyaltiumlib/schlib/records/SchComponent.py
pyaltiumlib/schlib/records/SchDesignator.py
pyaltiumlib/schlib/records/SchEllipse.py
pyaltiumlib/schlib/records/SchEllipticalArc.py
pyaltiumlib/schlib/records/SchImplementationList.py
pyaltiumlib/schlib/records/SchLabel.py
pyaltiumlib/schlib/records/SchLine.py
pyaltiumlib/schlib/records/SchParameter.py
pyaltiumlib/schlib/records/SchPin.py
pyaltiumlib/schlib/records/SchPolygon.py
pyaltiumlib/schlib/records/SchPolyline.py
pyaltiumlib/schlib/records/SchRectangle.py
pyaltiumlib/schlib/records/SchRoundRectangle.py
pyaltiumlib/schlib/records/__init__.py
pyaltiumlib/schlib/records/base.py
pyaltiumlib-0.6.1.dist-info/licenses/LICENSE.txt
pyaltiumlib-0.6.1.dist-info/METADATA
pyaltiumlib-0.6.1.dist-info/WHEEL
pyaltiumlib-0.6.1.dist-info/top_level.txt
pyaltiumlib-0.6.1.dist-info/RECORD
