Metadata-Version: 2.4
Name: pyaltiumlib
Version: 0.6.1
Summary: PyAltiumLib is a tool to read Altium Designer library files.
Home-page: https://github.com/ChrisHoyer/pyAltiumLib.git
Author: Chris Hoyer
Author-email: info@chrishoyer.de
Requires-Python: >=3.7
License-File: LICENSE.txt
Requires-Dist: olefile>=0.47
Requires-Dist: svgwrite>=1.4.3
Dynamic: author
Dynamic: author-email
Dynamic: description
Dynamic: description-content-type
Dynamic: home-page
Dynamic: license-file
Dynamic: requires-dist
Dynamic: requires-python
Dynamic: summary
